Workbook
Name Slicer___Contribution: #N/A
Name Slicer_Category: #N/A
Name Slicer_City: #N/A
Name Slicer_Months__Order_Date: #N/A
Name Slicer_Product: #N/A
Name Slicer_Sum_Of_Product: #N/A
Name Slicer_Total_Amount: #N/A
Name Slicer_Total_Amount1: #N/A
Name Slicer_Total_Amount2: #N/A

Sheet Pivot Chart 1
A2: Category | B2: Sum of Total Amount
A3: Accessories | B3: 4559752
A4: Education | B4: 3218358
A5: Electronics | B5: 18051230
A6: Fashion | B6: 7071377
A7: Furniture | B7: 2105733
A8: Home | B8: 3567955
A9: Grand Total | B9: 38574405

Sheet Pivot Chart 2
A2: Row Labels | B2: Sum of Total Amount
A3: Jan | B3: 9229930
A4: Feb | B4: 6009441
A5: Mar | B5: 6770966
A6: Apr | B6: 5819990
A7: May | B7: 7171131
A8: Jun | B8: 3572947
A9: Grand Total | B9: 38574405

Sheet Pivot Table 3
A1: Shop Branch | B1: Each Branch Sales
A2: Bangalore | B2: 5370704
A3: Chennai | B3: 6086266
A4: Delhi | B4: 5161477
A5: Hyderabad | B5: 4976827
A6: Kolkata | B6: 5600672
A7: Mumbai | B7: 5174869
A8: Pune | B8: 6203590
A9: Grand Total | B9: 38574405

Sheet Pivot Table 4
A3: Product Category | B3: Sum Of Product | C3: Sum of % Contribution
A4: Bag | B4: 2064608 | C4: 0.053522744
A5: Book | B5: 3218358 | C5: 0.083432473
A6: Chair | B6: 2105733 | C6: 0.054588865
A7: Headphones | B7: 3711749 | C7: 0.096223104
A8: Keyboard | B8: 2773395 | C8: 0.071897285
A9: Laptop | B9: 3695395 | C9: 0.095799145
A10: Mixer | B10: 3567955 | C10: 0.092495399
A11: Mobile | B11: 4702760 | C11: 0.121914
A12: Shoes | B12: 3375138 | C12: 0.087496826
A13: Tablet | B13: 3167931 | C13: 0.082125207
A14: total | B14: 38574405 | C14: 1
A15: T-Shirt | B15: 3696239 | C15: 0.095821024
... A17: Grand Total | B17: 77148810 | C17: 2

Sheet 4 Pivot Reference
A1: Product | B1: Month | C1: Quantity | D1: Price
A2: Keyboard | B2: January | C2: 1 | D2: 37967
A3: Keyboard | B3: May | C3: 5 | D3: 11247 | K3: Row Labels | L3: Sum of Quantity | M3: Sum of Price
A4: Bag | B4: January | C4: 5 | D4: 16393 | K4: January | L4: 321 | M4: 2933996
A5: Shoes | B5: January | C5: 3 | D5: 45821 | K5: Bag | L5: 16 | M5: 121122
A6: Mobile | B6: May | C6: 4 | D6: 22075 | K6: Book | L6: 26 | M6: 311878
A7: Mobile | B7: January | C7: 5 | D7: 42377 | K7: Chair | L7: 15 | M7: 130429
A8: Watch | B8: January | C8: 1 | D8: 21701 | K8: Headphones | L8: 26 | M8: 231187
A9: Headphones | B9: March | C9: 2 | D9: 46987 | K9: Keyboard | L9: 30 | M9: 277097
A10: Keyboard | B10: February | C10: 5 | D10: 30497 | K10: Laptop | L10: 30 | M10: 232262
A11: T-Shirt | B11: April | C11: 1 | D11: 47360 | K11: Mixer | L11: 35 | M11: 264645
A12: Book | B12: May | C12: 4 | D12: 44317 | K12: Mobile | L12: 39 | M12: 278178
A13: Tablet | B13: March | C13: 3 | D13: 35810 | K13: Shoes | L13: 34 | M13: 376242
A14: Bag | B14: January | C14: 1 | D14: 48794 | K14: Tablet | L14: 20 | M14: 211604
A15: Mobile | B15: March | C15: 4 | D15: 30177 | K15: T-Shirt | L15: 29 | M15: 260499
... A82: T-Shirt | B82: April | C82: 1 | D82: 46209 | K82: Grand Total | L82: 1508 | M82: 12850256
A83: Laptop | B83: March | C83: 1 | D83: 35696
A84: Mobile | B84: January | C84: 5 | D84: 3461
A85: Shoes | B85: January | C85: 5 | D85: 46388
A86: Watch | B86: April | C86: 1 | D86: 33565
A87: Headphones | B87: March | C87: 5 | D87: 28257
A88: Watch | B88: January | C88: 4 | D88: 46335
A89: Watch | B89: March | C89: 3 | D89: 33267
A90: Headphones | B90: January | C90: 1 | D90: 29290
A91: Tablet | B91: March | C91: 3 | D91: 47354
A92: Laptop | B92: April | C92: 1 | D92: 26480
A93: T-Shirt | B93: February | C93: 1 | D93: 17191
A94: Mixer | B94: April | C94: 1 | D94: 47185
... A501: Chair | B501: FEBRUARY | C501: 4 | D501: 35958

Sheet Sparkline
A1: Purchase Total Amount | B1: JAN | C1: FEB | D1: MAR | E1: APR | F1: MAY | G1: JUN | H1: SPARKLINE
A2: Bag | B2: 121122 | C2: 150230 | D2: 121531 | E2: 138713 | F2: 193497 | G2: 195628
A3: Book | B3: 311878 | C3: 137443 | D3: 117214 | E3: 175400 | F3: 286465 | G3: 56014
A4: Chair | B4: 231187 | C4: 181558 | D4: 85966 | E4: 85620 | F4: 110015 | G4: 109421
A5: Headphones | B5: 277097 | C5: 157067 | D5: 187329 | E5: 215937 | F5: 289050 | G5: 154109
A6: Keyboard | B6: 232262 | C6: 142057 | D6: 94792 | E6: 116245 | F6: 274567 | G6: 78791
A7: Laptop | B7: 264645 | C7: 284376 | D7: 282565 | E7: 174324 | F7: 169770 | G7: 115296
A8: Mixer | B8: 278178 | C8: 155454 | D8: 2622705 | E8: 242386 | F8: 148840 | G8: 159925
A9: Mobile | B9: 376242 | C9: 209510 | D9: 142901 | E9: 354895 | F9: 253803 | G9: 122276
A10: Shoes | B10: 211604 | C10: 53250 | D10: 145482 | E10: 277932 | F10: 128653 | G10: 30365
A11: Tablet | B11: 260499 | C11: 232467 | D11: 183940 | E11: 111297 | F11: 136796 | G11: 126808
A12: T-Shirt | B12: 238853 | C12: 179434 | D12: 226186 | E12: 196649 | F12: 278210 | G12: 75054
A13: Watch | B13: 238853 | C13: 70083 | D13: 222216 | E13: 141434 | F13: 96953 | G13: 69466
A14: Total | B14: =SUM(B2:B13) -> 3042420 | C14: =SUM(C2:C13) -> 1952929 | D14: =SUM(D2:D13) -> 4432827 | E14: =SUM(E2:E13) -> 2230832 | F14: =SUM(F2:F13) -> 2366619 | G14: =SUM(G2:G13) -> 1293153

Sheet Data Alignment
A1: Customer ID | B1: Customer Name | C1: Product | D1: Category | E1: Quantity | F1: Price | G1: Total Amount | H1: City | I1: Payment | J1: Rating | K1: Month | L1: Year
A2: C0001 | B2: Suresh Reddy | C2: Keyboard | D2: Electronics | E2: 1 | F2: 37967 | G2: =SUM(F2*E2) -> 37967 | H2: Bangalore | I2: UPI | J2: 4.1 | K2: January | L2: 2026
A3: C0002 | B3: Kiran Kumar | C3: Keyboard | D3: Electronics | E3: 5 | F3: 11247 | G3: =SUM(F3*E3) -> 56235 | H3: Bangalore | I3: Cash on Delivery | J3: 3.2 | K3: May | L3: 2026
A4: C0003 | B4: Vikram Kumar | C4: Bag | D4: Accessories | E4: 5 | F4: 16393 | G4: =SUM(F4*E4) -> 81965 | H4: Bangalore | I4: Cash on Delivery | J4: 4.2 | K4: January | L4: 2026
A5: C0004 | B5: Pooja Kumar | C5: Shoes | D5: Fashion | E5: 3 | F5: 45821 | G5: =SUM(F5*E5) -> 137463 | H5: Delhi | I5: Cash on Delivery | J5: 3.2 | K5: January | L5: 2026
A6: C0005 | B6: Arjun Kumar | C6: Mobile | D6: Electronics | E6: 4 | F6: 22075 | G6: =SUM(F6*E6) -> 88300 | H6: Bangalore | I6: Cash on Delivery | J6: 4.5 | K6: May | L6: 2026
A7: C0006 | B7: Lakshmi Singh | C7: Mobile | D7: Electronics | E7: 5 | F7: 42377 | G7: =SUM(F7*E7) -> 211885 | H7: Chennai | I7: Debit Card | J7: 3 | K7: January | L7: 2026
A8: C0007 | B8: Sneha Singh | C8: Watch | D8: Accessories | E8: 1 | F8: 21701 | G8: =SUM(F8*E8) -> 21701 | H8: Delhi | I8: Credit Card | J8: 4.6 | K8: January | L8: 2026
A9: C0008 | B9: Neha Sharma | C9: Headphones | D9: Electronics | E9: 2 | F9: 46987 | G9: =SUM(F9*E9) -> 93974 | H9: Hyderabad | I9: UPI | J9: 4.3 | K9: March | L9: 2026
A10: C0009 | B10: Pooja Singh | C10: Keyboard | D10: Electronics | E10: 5 | F10: 30497 | G10: =SUM(F10*E10) -> 152485 | H10: Kolkata | I10: Cash on Delivery | J10: 3.1 | K10: February | L10: 2026
A11: C0010 | B11: Divya Kumar | C11: T-Shirt | D11: Fashion | E11: 1 | F11: 47360 | G11: =SUM(F11*E11) -> 47360 | H11: Delhi | I11: Credit Card | J11: 4.6 | K11: April | L11: 2026
A12: C0011 | B12: Riya Singh | C12: Book | D12: Education | E12: 4 | F12: 44317 | G12: =SUM(F12*E12) -> 177268 | H12: Kolkata | I12: UPI | J12: 3.7 | K12: May | L12: 2026
A13: C0012 | B13: Sneha Reddy | C13: Tablet | D13: Electronics | E13: 3 | F13: 35810 | G13: =SUM(F13*E13) -> 107430 | H13: Kolkata | I13: Credit Card | J13: 3.1 | K13: March | L13: 2026
... A501: C0500 | B501: Meera Reddy | C501: Chair | D501: Furniture | E501: 4 | F501: 35958 | G501: =SUM(F501*E501) -> 143832 | H501: Hyderabad | I501: Credit Card | J501: 4.2 | K501: FEBRUARY | L501: 2026

Sheet Online Shopping Customer Data
A1: Customer ID | B1: Customer Name | C1: Product | D1: Category | E1: Quantity | F1: Price | G1: Total Amount | H1: Order Date | I1: City | J1: Payment Mode | K1: Rating
A2: C0001 | B2: Suresh Reddy | C2: Keyboard | D2: Electronics | E2: 1 | F2: 37967 | G2: =SUM(F2*E2) -> 37967 | H2: 46024 | I2: Bangalore | J2: UPI | K2: 4.1
A3: C0002 | B3: Kiran Kumar | C3: Keyboard | D3: Electronics | E3: 5 | F3: 11247 | G3: =SUM(F3*E3) -> 56235 | H3: 46143 | I3: Bangalore | J3: Cash on Delivery | K3: 3.2
A4: C0003 | B4: Vikram Kumar | C4: Bag | D4: Accessories | E4: 5 | F4: 16393 | G4: =SUM(F4*E4) -> 81965 | H4: 46039 | I4: Bangalore | J4: Cash on Delivery | K4: 4.2
A5: C0004 | B5: Pooja Kumar | C5: Shoes | D5: Fashion | E5: 3 | F5: 45821 | G5: =SUM(F5*E5) -> 137463 | H5: 46047 | I5: Delhi | J5: Cash on Delivery | K5: 3.2
A6: C0005 | B6: Arjun Kumar | C6: Mobile | D6: Electronics | E6: 4 | F6: 22075 | G6: =SUM(F6*E6) -> 88300 | H6: 46148 | I6: Bangalore | J6: Cash on Delivery | K6: 4.5
A7: C0006 | B7: Lakshmi Singh | C7: Mobile | D7: Electronics | E7: 5 | F7: 42377 | G7: =SUM(F7*E7) -> 211885 | H7: 46035 | I7: Chennai | J7: Debit Card | K7: 3
A8: C0007 | B8: Sneha Singh | C8: Watch | D8: Accessories | E8: 1 | F8: 21701 | G8: =SUM(F8*E8) -> 21701 | H8: 46040 | I8: Delhi | J8: Credit Card | K8: 4.6
A9: C0008 | B9: Neha Sharma | C9: Headphones | D9: Electronics | E9: 2 | F9: 46987 | G9: =SUM(F9*E9) -> 93974 | H9: 46110 | I9: Hyderabad | J9: UPI | K9: 4.3
A10: C0009 | B10: Pooja Singh | C10: Keyboard | D10: Electronics | E10: 5 | F10: 30497 | G10: =SUM(F10*E10) -> 152485 | H10: 46069 | I10: Kolkata | J10: Cash on Delivery | K10: 3.1
A11: C0010 | B11: Divya Kumar | C11: T-Shirt | D11: Fashion | E11: 1 | F11: 47360 | G11: =SUM(F11*E11) -> 47360 | H11: 46121 | I11: Delhi | J11: Credit Card | K11: 4.6
A12: C0011 | B12: Riya Singh | C12: Book | D12: Education | E12: 4 | F12: 44317 | G12: =SUM(F12*E12) -> 177268 | H12: 46166 | I12: Kolkata | J12: UPI | K12: 3.7
A13: C0012 | B13: Sneha Reddy | C13: Tablet | D13: Electronics | E13: 3 | F13: 35810 | G13: =SUM(F13*E13) -> 107430 | H13: 46111 | I13: Kolkata | J13: Credit Card | K13: 3.1
... A501: C0500 | B501: Meera Reddy | C501: Chair | D501: Furniture | E501: 4 | F501: 35958 | G501: =SUM(F501*E501) -> 143832 | H501: 46065 | I501: Hyderabad | J501: Credit Card | K501: 4.2
A506: Formula Calculation
A508: 1) Total Sales | B508: =SUM(G2:G501) -> 38574405
A510: 2) Maximum sales | B510: =MAX(G1:G501) -> 249840
A512: 3) Minimum Sales | B512: =MIN(G1:G501) -> 1161
A514: 4) Total Orders | B514: =COUNTA(G1:G501)-1 -> 500
A516: 5)Unique Customers | B516: =COUNTA(_xlfn.UNIQUE(B1:B501)) -> 100
A518: 6)Rating Average | B518: =AVERAGE(K1:K501) -> 4.0046
A520: 7)Index | B520: =INDEX(G1:G501,15) -> 120708
A522: 8)Match | B522: =MATCH(B38,$B$1:B501,0) -> 38
A524: 9)Index Match | B524: Book | C524: =INDEX($G$1:G501,MATCH(B524,$C$1:$C$501)) -> 65416
A526: 10) lookup value | B526: Vlookup value | C526: Suresh Sharma | D526: =VLOOKUP(B488,B1:G501,5,"false") -> 46523
B527: Hlookup value | C527: Rahul Singh | D527: =HLOOKUP(D1,B1:F501,478,"false") -> Electronics
A529: 11) Len | B529: Meera Reddy | C529: =LEN(B529) -> 11
A531: 12)upper | B531: Priya Sharma | C531: =UPPER(B531) -> PRIYA SHARMA
A533: 13)Lower | B533: Priya Sharma | C533: =LOWER(B533) -> priya sharma
A535: 14)Proper | B535: Suresh Sharma | C535: =PROPER(B535) -> Suresh Sharma
A537: 15)Left | B537: Suresh Sharma | C537: =LEFT(B537,4) -> Sure
A539: 16)Right | B539: Suresh Sharma | C539: =RIGHT(B539,5) -> harma
A541: 17)Mid | B541: Priya Singh | C541: =MID(B541,5,5) -> a Sin
A543: 18)Replace | B543: Priya Singh | C543: =REPLACE(B543,1,5,"Pooja") -> Pooja Singh
A545: 19)Date | B545: =TODAY() -> 46295 | C545: =NOW() -> 46295.631
A547: 20)Is Text | B547: =TODAY() -> 46295 | C547: =ISTEXT(B547) -> FALSE
A549: 21)concat | B549: Priya Singh | C549: =_xlfn.CONCAT(B549,C543) -> Priya SinghPooja Singh
B550: Pooja singh
A552: 22)Year | B552: 46199 | C552: =YEAR(B552) -> 2026
A554: 23)Drop down | B554: NO STOCK

Sheet Dashboard
D2: THE ONLINE SHOPPING ANALYTICS DASHBOARD 2026

Sheet Objective
H1: PROJECT OBJECTIVE
A3: The Online Shopping Analytics Dashboard
A10: Dataset Size
A16: Tool And Features Included

Sheet Dashboard (2)
A1: Online Shopping Analytics Dashboard | D1: Category | E1: Revenue
D2: Electronics | E2: =SUMIF('Online Shopping Customer Data'!D:D,"Electronics",'Online Shopping Customer Data'!K:K) -> 898
A3: Total Orders | B3: =COUNTA('Online Shopping Customer Data'!A2:A100) -> 99 | D3: Fashion | E3: =SUMIF('Online Shopping Customer Data'!D:D,"Fashion",'Online Shopping Customer Data'!K:K) -> 342.9
A4: Total Revenue | B4: =SUM('Online Shopping Customer Data'!K8:K100) -> 376.7 | D4: Accessories | E4: =SUMIF('Online Shopping Customer Data'!D:D,"Accessories",'Online Shopping Customer Data'!K:K) -> 286.2
A5: Average Rating | B5: =AVERAGE('Online Shopping Customer Data'!J8:J100) -> #DIV/0!
